pout2groups/Analyzer.py
pout2groups/OccamsRazorPreprocessor.py
pout2groups/OutputWriter.py
pout2groups/Parser.py
pout2groups/ProteinGrouping.py
pout2groups/ProteinSubGrouping.py
pout2groups/main.py
pout2groups-0.1.dist-info/METADATA
pout2groups-0.1.dist-info/WHEEL
pout2groups-0.1.dist-info/entry_points.txt
pout2groups-0.1.dist-info/top_level.txt
pout2groups-0.1.dist-info/RECORD
