Metadata-Version: 2.1
Name: pout2groups
Version: 0.1
Summary: A script to perform protein grouping on pout-files (generated by Percolator).
Home-page: UNKNOWN
Author: Pieter Verschaffelt
Author-email: pieter.verschaffelt@ugent.be
License: UNKNOWN
Platform: UNKNOWN
